{"stat.crouchOneCm":349,"achievement.exploreAllBiomes":{"value":0,"progress":["Deep Ocean","Ocean","Beach","Plains","River"]},"achievement.openInventory":8,"stat.climbOneCm":76,"stat.fallOneCm":2342,"stat.mineBlock.minecraft.diamond_ore":7,"stat.flyOneCm":6990,"stat.timeSinceDeath":59308,"stat.playOneMinute":59308,"stat.leaveGame":4,"stat.diveOneCm":15199,"stat.jump":113,"stat.swimOneCm":12448,"stat.walkOneCm":45177,"stat.useItem.minecraft.iron_pickaxe":7,"stat.craftItem.minecraft.planks":128,"stat.useItem.minecraft.carrot":3,"stat.sprintOneCm":14810}