{"stat.crouchOneCm":163,"achievement.exploreAllBiomes":{"value":0,"progress":["Deep Ocean","Ocean","Beach","Plains"]},"achievement.openInventory":8,"stat.climbOneCm":1284,"stat.fallOneCm":2659,"stat.flyOneCm":655,"stat.mineBlock.minecraft.iron_ore":4,"stat.mineBlock.minecraft.gold_ore":2,"stat.timeSinceDeath":17305,"stat.playOneMinute":47361,"stat.leaveGame":13,"stat.diveOneCm":21075,"stat.deaths":1,"stat.jump":284,"stat.swimOneCm":11172,"stat.mineBlock.minecraft.stone":47,"stat.walkOneCm":217376,"stat.useItem.minecraft.iron_pickaxe":60,"stat.mineBlock.minecraft.redstone_ore":2,"stat.mineBlock.minecraft.coal_ore":5,"stat.sprintOneCm":713}