{"stat.crouchOneCm":470,"achievement.exploreAllBiomes":{"value":0,"progress":["Ocean","Plains"]},"achievement.openInventory":1,"stat.fallOneCm":691,"stat.mineBlock.minecraft.iron_ore":1,"stat.flyOneCm":4856,"stat.mineBlock.minecraft.gold_ore":2,"stat.timeSinceDeath":5452,"stat.playOneMinute":5452,"stat.leaveGame":2,"stat.jump":24,"stat.mineBlock.minecraft.stone":52,"stat.walkOneCm":29221,"stat.useItem.minecraft.iron_pickaxe":59,"stat.mineBlock.minecraft.redstone_ore":1,"stat.mineBlock.minecraft.coal_ore":3,"stat.sprintOneCm":10401}